prodia/__init__.py
prodia/exceptions.py
prodia/resources/__init__.py
prodia/resources/engine.py
prodia/resources/stablediffusion.py
prodia/resources/stablediffusionxl.py
prodia/resources/upscale.py
prodia/util.py
prodia-4.2.dist-info/LICENSE
prodia-4.2.dist-info/METADATA
prodia-4.2.dist-info/WHEEL
prodia-4.2.dist-info/RECORD
